notifydict.py
notifydict-0.1.2.dist-info/DESCRIPTION.rst
notifydict-0.1.2.dist-info/METADATA
notifydict-0.1.2.dist-info/RECORD
notifydict-0.1.2.dist-info/WHEEL
notifydict-0.1.2.dist-info/metadata.json
notifydict-0.1.2.dist-info/top_level.txt
