Metadata-Version: 2.0
Name: notifydict
Version: 0.1.2
Summary: a dictionary which will fire a callback if its changed
Home-page: https://github.com/gesellkammer/notifydict
Author: Eduardo Moguillansky
Author-email: eduardo.moguillansky@gmail.com
License: UNKNOWN
Platform: UNKNOWN
Classifier: Development Status :: 3 - Alpha
Classifier: Intended Audience :: Education
Classifier: Intended Audience :: Developers
Classifier: Intended Audience :: Information Technology
Classifier: License :: OSI Approved :: MIT License
Classifier: Programming Language :: Python
Classifier: Topic :: Text Processing :: General
